{"stats":{"minecraft:killed_by":{"minecraft:player":1},"minecraft:used":{"minecraft:water_bucket":1,"minecraft:netherite_sword":3,"minecraft:ender_pearl":9,"minecraft:diamond_axe":2,"minecraft:dirt":1,"minecraft:netherite_leggings":5,"minecraft:shears":1,"minecraft:diamond_pickaxe":2345,"minecraft:golden_leggings":6,"minecraft:diamond_sword":1,"minecraft:bow":4,"minecraft:red_carpet":1,"minecraft:golden_carrot":19,"minecraft:netherite_pickaxe":23,"minecraft:bucket":1,"minecraft:lapis_block":16,"minecraft:white_concrete":1,"minecraft:cobweb":1},"minecraft:custom":{"minecraft:interact_with_smithing_table":4,"minecraft:interact_with_anvil":25,"minecraft:traded_with_villager":143,"minecraft:interact_with_crafting_table":35,"minecraft:leave_game":6,"minecraft:time_since_death":200528,"minecraft:climb_one_cm":1120,"minecraft:time_since_rest":200529,"minecraft:sprint_one_cm":521946,"minecraft:open_enderchest":65,"minecraft:damage_taken":416,"minecraft:walk_one_cm":111354,"minecraft:drop":47,"minecraft:damage_dealt":268,"minecraft:swim_one_cm":4543,"minecraft:fly_one_cm":900787,"minecraft:crouch_one_cm":30884,"minecraft:play_time":251702,"minecraft:deaths":1,"minecraft:sneak_time":16670,"minecraft:walk_under_water_one_cm":6849,"minecraft:boat_one_cm":3485,"minecraft:jump":3191,"minecraft:walk_on_water_one_cm":2163,"minecraft:total_world_time":251702,"minecraft:fall_one_cm":99492,"minecraft:inspect_dispenser":2},"minecraft:picked_up":{"minecraft:netherite_boots":1,"minecraft:golden_carrot":62,"minecraft:golden_leggings":1,"minecraft:gold_block":3,"minecraft:oak_log":2,"minecraft:ancient_debris":1,"minecraft:lapis_lazuli":74,"minecraft:lapis_block":3,"minecraft:netherite_leggings":1,"minecraft:netherite_scrap":4,"minecraft:oak_sign":3,"minecraft:cracked_stone_bricks":2,"minecraft:gold_nugget":2,"minecraft:iron_ingot":1,"minecraft:oak_planks":4,"minecraft:mace":1,"minecraft:diamond":1047,"minecraft:netherite_helmet":1,"minecraft:golden_apple":115,"minecraft:gold_ingot":26,"minecraft:emerald":1,"minecraft:netherite_chestplate":1,"minecraft:coal":2,"minecraft:ender_pearl":6},"minecraft:mined":{"minecraft:diamond_ore":102,"minecraft:red_carpet":1,"minecraft:emerald_ore":826,"minecraft:grass_block":1,"minecraft:oxidized_copper":3,"minecraft:white_concrete":1,"minecraft:glass":13,"minecraft:lapis_ore":217,"minecraft:spawner":129,"minecraft:lapis_block":623,"minecraft:iron_ore":2,"minecraft:diamond_block":176,"minecraft:gold_block":32,"minecraft:pointed_dripstone":2,"minecraft:oak_log":5,"minecraft:cobweb":1,"minecraft:ancient_debris":24,"minecraft:gold_ore":34,"minecraft:emerald_block":195},"minecraft:crafted":{"minecraft:oak_planks":20,"minecraft:netherite_pickaxe":1,"minecraft:diamond_sword":1,"minecraft:arrow":64,"minecraft:diamond_axe":1,"minecraft:experience_bottle":128,"minecraft:cobweb":64,"minecraft:enchanted_book":32,"minecraft:air":0,"minecraft:diamond_block":100,"minecraft:diamond":9,"minecraft:diamond_helmet":1,"minecraft:diamond_leggings":1,"minecraft:golden_apple":64,"minecraft:diamond_pickaxe":3,"minecraft:emerald_block":192,"minecraft:shield":1,"minecraft:stick":24,"minecraft:ender_pearl":48,"minecraft:diamond_boots":1,"minecraft:water_bucket":2,"minecraft:netherite_ingot":7,"minecraft:netherite_upgrade_smithing_template":1,"minecraft:splash_potion":7,"minecraft:shears":1,"minecraft:lapis_block":259,"minecraft:diamond_chestplate":1},"minecraft:dropped":{"minecraft:iron_ingot":2,"minecraft:emerald_block":3,"minecraft:lapis_lazuli":89,"minecraft:oak_log":2,"minecraft:diamond":342,"minecraft:pointed_dripstone":2,"minecraft:oak_planks":6,"minecraft:cracked_stone_bricks":2,"minecraft:oak_sign":3,"minecraft:coal":2,"minecraft:golden_apple":64,"minecraft:stick":2,"minecraft:emerald":2,"minecraft:gold_block":3,"minecraft:gold_nugget":2,"minecraft:lapis_block":8,"minecraft:gold_ingot":93}},"DataVersion":3839}